pyqt_helper/__init__.py
pyqt_helper/__main__.py
pyqt_helper/pyqt_helper.py
pyqt_helper-0.0.3.dist-info/LICENSE
pyqt_helper-0.0.3.dist-info/METADATA
pyqt_helper-0.0.3.dist-info/WHEEL
pyqt_helper-0.0.3.dist-info/top_level.txt
pyqt_helper-0.0.3.dist-info/RECORD
