Metadata-Version: 2.1
Name: pyqt-helper
Version: 0.0.3
Summary: PyQt Helper auto-generates boiler plate code for interacting with PyQt widgets.
Home-page: https://github.com/morefigs/pyqt-helper
Author: morefigs
Author-email: morefigs@gmail.com
License: MIT
Keywords: python,python3,pyqt,pyqt5,ui,code-generation
Platform: UNKNOWN
Classifier: Development Status :: 4 - Beta
Classifier: Intended Audience :: Developers
Classifier: License :: OSI Approved :: MIT License
Classifier: Natural Language :: English
Classifier: Operating System :: MacOS
Classifier: Operating System :: Microsoft :: Windows
Classifier: Operating System :: POSIX :: Linux
Classifier: Programming Language :: Python
Classifier: Topic :: Software Development :: Code Generators
Classifier: Topic :: Software Development :: User Interfaces
Requires-Dist: pyqt5
